<?xml version="1.0" encoding="UTF-8"?>
<beans xmlns="http://www.springframework.org/schema/beans"
       xmlns:xsi="http://www.w3.org/2001/XMLSchema-instance"
       xsi:schemaLocation="http://www.springframework.org/schema/beans http://www.springframework.org/schema/beans/spring-beans.xsd">
       
	<bean class="org.springframework.beans.factory.config.PropertyPlaceholderConfigurer">
		<property name="locations">
			<list>
				<value>classpath*:system.properties</value>
			</list>
		</property>
	</bean>
		
	<bean id="executor" class="org.apache.catalina.core.StandardThreadExecutor" init-method="initInternal"
		destroy-method="destroyInternal">
        <property name="minSpareThreads" value="${web.min.threads:100}" />
		<property name="maxThreads" value="${web.max.threads:1000}" />
		<property name="maxQueueSize" value="${web.max.queued:2147483647}" />
    </bean>	
    
    <bean id="tomcatServer" class="com.appleframework.boot.tomcat.EmbeddedTomcat" destroy-method="destroy" 
    	init-method="init">
        <property name="contextPath" value="${web.context}" />
        <property name="tomcatPort" value="${web.port}" />
    </bean>
    
</beans>